{
  "slug": "granfondo-leiria",
  "race_name": "Granfondo Leiria Region \u2013 Sico Lands",
  "distance_mi": 92.0,
  "demands": {
    "durability": 4,
    "climbing": 1,
    "vo2_power": 6,
    "threshold": 7,
    "technical": 0,
    "heat_resilience": 0,
    "altitude": 6,
    "race_specificity": 9
  },
  "top_categories": [
    {
      "category": "VO2max",
      "score": 100,
      "workouts": [
        "5x3 VO2 Classic",
        "Descending VO2 Pyramid",
        "Norwegian 4x8"
      ],
      "workout_context": "6,500ft of climbing means repeated surges above threshold. VO2max work is how you survive the fifth climb, not just the first."
    },
    {
      "category": "Race_Simulation",
      "score": 82,
      "workouts": [
        "Breakaway Simulation",
        "Variable Pace Chaos",
        "Sector Simulation"
      ],
      "workout_context": "Race-pace efforts that mimic Granfondo Leiria Region \u2013 Sico Lands' demands. Pacing, fueling, and tactical decisions under fatigue. Practice the race before March."
    },
    {
      "category": "Durability",
      "score": 77,
      "workouts": [
        "Tired VO2max",
        "Double Day Simulation",
        "Progressive Fatigue"
      ],
      "workout_context": "At mile 60 of 92, glycogen is gone. This workout teaches your body to produce watts on fumes."
    },
    {
      "category": "TT_Threshold",
      "score": 68,
      "workouts": [
        "Single Sustained Threshold",
        "Threshold Ramps",
        "Descending Threshold"
      ],
      "workout_context": "71ft/mi means long efforts at or near FTP on every climb. If your threshold cracks at minute 15, you'll walk the rest."
    },
    {
      "category": "G_Spot",
      "score": 56,
      "workouts": [
        "G-Spot Standard",
        "G-Spot Extended",
        "Criss-Cross"
      ],
      "workout_context": "88\u201392% FTP is where you'll spend the hardest sustained miles of Granfondo Leiria Region \u2013 Sico Lands. Train it until it feels boring."
    },
    {
      "category": "Gravel_Specific",
      "score": 55,
      "workouts": [
        "Surge and Settle",
        "Terrain Microbursts"
      ],
      "workout_context": "Granfondo Leiria Region \u2013 Sico Lands' mixed terrain forces constant power changes. Surge over the rough stuff, settle on the smooth, repeat for 92 miles."
    },
    {
      "category": "Endurance",
      "score": 52,
      "workouts": [
        "Pre-Race Openers",
        "Terrain Simulation Z2"
      ],
      "workout_context": "Every hard session works better with a bigger aerobic base. At 92 miles, base fitness is the difference between racing and surviving."
    },
    {
      "category": "Blended",
      "score": 45,
      "workouts": [
        "Z2 + VO2 Combo",
        "Endurance with Spikes"
      ],
      "workout_context": "Endurance with intensity spikes baked in. Exactly what 6,500ft of climbing on mixed terrain does to your power file on race day."
    },
    {
      "category": "Norwegian_Double",
      "score": 42,
      "workouts": [
        "Norwegian 4x8 Classic",
        "Double Threshold"
      ],
      "workout_context": "Two threshold sessions per week without the recovery cost of VO2max work. For 92 miles, sustainable FTP gains matter more than peak power."
    },
    {
      "category": "Over_Under",
      "score": 39,
      "workouts": [
        "Classic Over-Unders",
        "Ladder Over-Unders"
      ],
      "workout_context": "At Granfondo Leiria Region \u2013 Sico Lands, surges push you above threshold and you have to recover while still riding. Over-unders train exactly that."
    },
    {
      "category": "Anaerobic_Capacity",
      "score": 36,
      "workouts": [
        "2min Killers",
        "90sec Repeats"
      ],
      "workout_context": "Short, max efforts are unavoidable. Punchy climbs, gap closures, attacks on mixed terrain. If you haven't trained them, you'll crack."
    },
    {
      "category": "Tempo",
      "score": 33,
      "workouts": [
        "Tempo Blocks",
        "Extended Tempo"
      ],
      "workout_context": "Tempo is Granfondo Leiria Region \u2013 Sico Lands' race pace. The wattage you'll hold for 92 miles on mixed terrain. Train it until it's automatic."
    }
  ],
  "race_overlay": {
    "nutrition": "Target 60\u201380g carbs/hour for Granfondo Leiria Region \u2013 Sico Lands\u2019s 92 miles. Start fueling within the first 30 minutes \u2014 early fueling prevents late-race collapse. Bonking at mile 60 is a nutrition failure, not a fitness failure.",
    "altitude": "Moderate altitude at Granfondo Leiria Region \u2013 Sico Lands. Arrive 2\u20133 days early. Reduce intensity expectations by 5\u201310%. Hydrate aggressively."
  },
  "pack_summary": "This 10-workout pack focuses on VO2max, Race Simulation, and Durability to prepare you for 92 miles of mixed terrain in Pombal, Portugal.",
  "generated_at": "2026-06-09"
}