{
  "slug": "inthanon-challenge",
  "race_name": "Inthanon Challenge",
  "distance_mi": 30.0,
  "demands": {
    "durability": 1,
    "climbing": 2,
    "vo2_power": 6,
    "threshold": 3,
    "technical": 0,
    "heat_resilience": 0,
    "altitude": 8,
    "race_specificity": 9
  },
  "top_categories": [
    {
      "category": "VO2max",
      "score": 100,
      "workouts": [
        "5x3 VO2 Classic",
        "Descending VO2 Pyramid",
        "Norwegian 4x8"
      ],
      "workout_context": "8,415ft of climbing means repeated surges above threshold. VO2max work is how you survive the fifth climb, not just the first."
    },
    {
      "category": "Race_Simulation",
      "score": 71,
      "workouts": [
        "Breakaway Simulation",
        "Variable Pace Chaos",
        "Sector Simulation"
      ],
      "workout_context": "Race-pace efforts that mimic Inthanon Challenge's demands. Pacing, fueling, and tactical decisions under fatigue. Practice the race before February."
    },
    {
      "category": "Gravel_Specific",
      "score": 47,
      "workouts": [
        "Surge and Settle",
        "Terrain Microbursts"
      ],
      "workout_context": "Inthanon Challenge's mixed terrain forces constant power changes. Surge over the rough stuff, settle on the smooth, repeat for 30 miles."
    },
    {
      "category": "Durability",
      "score": 43,
      "workouts": [
        "Tired VO2max",
        "Double Day Simulation",
        "Progressive Fatigue"
      ],
      "workout_context": "30 miles on mixed terrain burns energy faster than the distance suggests. Train the fade resistance now."
    },
    {
      "category": "Endurance",
      "score": 37,
      "workouts": [
        "Pre-Race Openers",
        "Terrain Simulation Z2"
      ],
      "workout_context": "Base fitness for Inthanon Challenge. Without this, the hard workouts break you down instead of building you up."
    },
    {
      "category": "TT_Threshold",
      "score": 32,
      "workouts": [
        "Single Sustained Threshold",
        "Threshold Ramps",
        "Descending Threshold"
      ],
      "workout_context": "280ft/mi means long efforts at or near FTP on every climb. If your threshold cracks at minute 15, you'll walk the rest."
    },
    {
      "category": "Anaerobic_Capacity",
      "score": 32,
      "workouts": [
        "2min Killers",
        "90sec Repeats"
      ],
      "workout_context": "Short, max efforts are unavoidable. Punchy climbs, gap closures, attacks on mixed terrain. If you haven't trained them, you'll crack."
    },
    {
      "category": "Blended",
      "score": 28,
      "workouts": [
        "Z2 + VO2 Combo",
        "Endurance with Spikes"
      ],
      "workout_context": "Endurance with intensity spikes baked in. Exactly what 8,415ft of climbing on mixed terrain does to your power file on race day."
    },
    {
      "category": "Over_Under",
      "score": 25,
      "workouts": [
        "Classic Over-Unders",
        "Ladder Over-Unders"
      ],
      "workout_context": "At Inthanon Challenge, surges push you above threshold and you have to recover while still riding. Over-unders train exactly that."
    },
    {
      "category": "G_Spot",
      "score": 25,
      "workouts": [
        "G-Spot Standard",
        "G-Spot Extended",
        "Criss-Cross"
      ],
      "workout_context": "88\u201392% FTP is where you'll spend the hardest sustained miles of Inthanon Challenge. Train it until it feels boring."
    },
    {
      "category": "Critical_Power",
      "score": 24,
      "workouts": [
        "Above CP Repeats",
        "W-Prime Depletion"
      ],
      "workout_context": "How long can you hold 105% FTP before you blow? At Inthanon Challenge, that number decides whether you bridge or get dropped."
    },
    {
      "category": "LT1_MAF",
      "score": 21,
      "workouts": [
        "MAF Capped Ride",
        "LT1 Assessment"
      ],
      "workout_context": "Below LT1, you burn fat. Above it, you burn glycogen. For 30 miles, a higher LT1 means slower bonk."
    }
  ],
  "race_overlay": {
    "nutrition": "Standard hydration and fueling. One bottle per hour minimum. Gel or bar every 45 minutes at race intensity.",
    "altitude": "Inthanon Challenge with 8,415ft of climbing, much of it above 8,000ft demands altitude preparation. Arrive 5\u20137 days early for acclimatization. Expect 5\u201315% power reduction at altitude. Increase iron intake 4 weeks out. Hydrate aggressively \u2014 altitude increases fluid loss by 20\u201340%."
  },
  "pack_summary": "This 10-workout pack focuses on VO2max, Race Simulation, and Gravel Specific to prepare you for 30 miles of mixed terrain in Chom Thong, Chiang Mai, Thailand.",
  "generated_at": "2026-06-09"
}