{
  "slug": "manali-khardungla-cycling-championship",
  "race_name": "Manali-Khardung La Cycling Championship",
  "distance_mi": 347.0,
  "demands": {
    "durability": 10,
    "climbing": 10,
    "vo2_power": 6,
    "threshold": 5,
    "technical": 8,
    "heat_resilience": 0,
    "altitude": 10,
    "race_specificity": 10
  },
  "top_categories": [
    {
      "category": "Durability",
      "score": 100,
      "workouts": [
        "Tired VO2max",
        "Double Day Simulation",
        "Progressive Fatigue"
      ],
      "workout_context": "347 miles. Your legs will beg to quit after 120. This trains the power output you need from mile 130 onward."
    },
    {
      "category": "Gravel_Specific",
      "score": 98,
      "workouts": [
        "Surge and Settle",
        "Terrain Microbursts"
      ],
      "workout_context": "Manali-Khardung La Cycling Championship's mixed terrain forces constant power changes. Surge over the rough stuff, settle on the smooth, repeat for 347 miles."
    },
    {
      "category": "VO2max",
      "score": 96,
      "workouts": [
        "5x3 VO2 Classic",
        "Descending VO2 Pyramid",
        "Norwegian 4x8"
      ],
      "workout_context": "35,000ft of climbing means repeated surges above threshold. VO2max work is how you survive the fifth climb, not just the first."
    },
    {
      "category": "Race_Simulation",
      "score": 93,
      "workouts": [
        "Breakaway Simulation",
        "Variable Pace Chaos",
        "Sector Simulation"
      ],
      "workout_context": "Race-pace efforts that mimic Manali-Khardung La Cycling Championship's demands. Pacing, fueling, and tactical decisions under fatigue. Practice the race before August."
    },
    {
      "category": "Endurance",
      "score": 78,
      "workouts": [
        "Pre-Race Openers",
        "Terrain Simulation Z2"
      ],
      "workout_context": "Every hard session works better with a bigger aerobic base. At 347 miles, base fitness is the difference between racing and surviving."
    },
    {
      "category": "Over_Under",
      "score": 72,
      "workouts": [
        "Classic Over-Unders",
        "Ladder Over-Unders"
      ],
      "workout_context": "At Manali-Khardung La Cycling Championship, surges push you above threshold and you have to recover while still riding. Over-unders train exactly that."
    },
    {
      "category": "Mixed_Climbing",
      "score": 67,
      "workouts": [
        "Seated/Standing Climbs",
        "Variable Grade Simulation"
      ],
      "workout_context": "35,000ft of climbing on grades that change every minute. You need to switch from seated to standing without losing rhythm."
    },
    {
      "category": "TT_Threshold",
      "score": 67,
      "workouts": [
        "Single Sustained Threshold",
        "Threshold Ramps",
        "Descending Threshold"
      ],
      "workout_context": "101ft/mi means long efforts at or near FTP on every climb. If your threshold cracks at minute 15, you'll walk the rest."
    },
    {
      "category": "HVLI_Extended",
      "score": 56,
      "workouts": [
        "HVLI Extended Z2",
        "Multi-Hour Z2",
        "Back-to-Back Long"
      ],
      "workout_context": "347 miles rewards fat oxidation. This volume work shifts your fuel mix so you're still burning fat at hour 5, not bonking at hour 3."
    },
    {
      "category": "Blended",
      "score": 56,
      "workouts": [
        "Z2 + VO2 Combo",
        "Endurance with Spikes"
      ],
      "workout_context": "Endurance with intensity spikes baked in. Exactly what 35,000ft of climbing on mixed terrain does to your power file on race day."
    },
    {
      "category": "Critical_Power",
      "score": 56,
      "workouts": [
        "Above CP Repeats",
        "W-Prime Depletion"
      ],
      "workout_context": "How long can you hold 105% FTP before you blow? At Manali-Khardung La Cycling Championship, that number decides whether you bridge or get dropped."
    },
    {
      "category": "G_Spot",
      "score": 50,
      "workouts": [
        "G-Spot Standard",
        "G-Spot Extended",
        "Criss-Cross"
      ],
      "workout_context": "88\u201392% FTP is where you'll spend the hardest sustained miles of Manali-Khardung La Cycling Championship. Train it until it feels boring."
    }
  ],
  "race_overlay": {
    "nutrition": "Ultra-distance fueling for 347 miles: 80\u2013100g carbs/hour from mile 1 \u2014 don\u2019t wait until you\u2019re hungry. Practice your exact race-day nutrition in every long training ride. Carry backup calories. 347 miles burns 8,000\u201312,000+ calories \u2014 you cannot replace them all, but you must try.",
    "altitude": "Manali-Khardung La Cycling Championship with 35,000ft of climbing, much of it above 8,000ft demands altitude preparation. Arrive 5\u20137 days early for acclimatization. Expect 5\u201315% power reduction at altitude. Increase iron intake 4 weeks out. Hydrate aggressively \u2014 altitude increases fluid loss by 20\u201340%.",
    "terrain": "Highly technical terrain at Manali-Khardung La Cycling Championship demands practice on similar surfaces. Ride mixed terrain at race-day cadence weekly. Practice cornering, descending, and power delivery on unstable surfaces. Dial in tire pressure before race week \u2014 5 PSI wrong costs you 15+ minutes over 347 miles."
  },
  "pack_summary": "This 10-workout pack focuses on Durability, Gravel Specific, and VO2max to prepare you for 347 miles of mixed terrain in Manali to Leh, Himachal Pradesh / Ladakh, India.",
  "generated_at": "2026-06-25"
}