{
  "race": {
    "name": "GFNY Bremen",
    "slug": "gfny-bremen",
    "display_name": "GFNY Bremen",
    "tagline": "Flat, fast, and windy: Be a Pro for a Day on North German roads",
    "vitals": {
      "distance_km": 112.0,
      "distance_mi": 69.6,
      "elevation_m": 300,
      "elevation_ft": 984.0,
      "location": "Bremen, Germany",
      "location_badge": "Tabakquartier Bremen",
      "country": "Germany",
      "date": "August 30",
      "date_specific": "August 30, 2026",
      "field_size": 1500,
      "start_format": null,
      "registration": "Open via bremen.gfny.com",
      "entry_fee": "Not specified",
      "feed_zones": "Maurten fueling stations",
      "cutoff_time": "Not specified",
      "lat": 53.1048,
      "lng": 8.8089,
      "route_options": [
        {
          "name": "Long Route",
          "distance_km": 112,
          "distance_mi": 69.6,
          "competitive": true
        },
        {
          "name": "Medium Route",
          "distance_km": 68,
          "distance_mi": 42.2,
          "competitive": false
        }
      ]
    },
    "climate": {
      "primary": "Temperate",
      "description": "North German late-summer: mild temperatures, potential wind challenges on exposed flat terrain[1][2][3]",
      "challenges": [
        "North German late-summer: mild temperatures, potential wind challenges on exposed flat terrain[1][2][3]"
      ]
    },
    "terrain": {
      "primary": "Flat",
      "surface": "Mostly flat North German roads with frequent false flats, 500m cobbles, farmland, forest, and small turny roads[1][2][3]",
      "technical_rating": 4,
      "features": [
        "Mostly flat North German roads with frequent false flats, 500m cobbles, farmland, forest, and small turny roads[1][2][3]"
      ]
    },
    "fondo_rating": {
      "distance": 3,
      "climbing": 1,
      "descent_technicality": 3,
      "climate_risk": 3,
      "organization": 4,
      "scenic_experience": 4,
      "community_culture": 4,
      "altitude": 1,
      "logistics": 4,
      "prestige": 3,
      "field_depth": 3,
      "value": 3,
      "expenses": 3,
      "road_surface": 4,
      "cultural_impact": 2,
      "overall_score": 64,
      "tier": 2,
      "tier_label": "TIER 2",
      "discipline": "gran_fondo",
      "prestige_override": null,
      "scoring_notes": "Migrated from gravel-race-automation. Original score: 61. adventure dimension dropped, road_surface added. Score recalculated: 64."
    },
    "climb_profile": {
      "total_climbs": null,
      "hc_climbs": null,
      "cat_1_climbs": null,
      "cat_2_climbs": null,
      "cat_3_climbs": null,
      "key_climbs": [],
      "profile_type": null,
      "king_of_mountain": null,
      "_needs_enrichment": true
    },
    "course_description": {
      "character": "Neutralized 0-4km to airport → racing km4-18 turny roads → double flat loop (farmland/forest/false flats/500m cobbles) → timing finish km106 sprint → neutralized 6km Ochtum River cooldown to Tabakquartier[1][2][3]",
      "signature_challenge": null,
      "suffering_zones": [
        "Wind-exposed flats (entire loops)",
        "500m cobbles historic sector",
        "False flats sorting groups"
      ]
    },
    "logistics": {
      "airport": "",
      "lodging_strategy": "",
      "transport": "Bremen Airport (BRE) on course km4. Hamburg (HAM) 1hr away. Tabakquartier central hub. Easy Euro access[1][2][5]",
      "food": "",
      "official_site": ""
    },
    "history": {
      "founded": 2025,
      "origin_story": "Inaugural 2025 (Aug 31) as GFNY Europe Championship with 1500 riders. 2026 edition Aug 30. Organized by GFNY Global Series[1][2][5]",
      "notable_moments": [],
      "reputation": ""
    },
    "biased_opinion": {
      "verdict": "",
      "summary": "GFNY Bremen delivers the franchise polish on a fast, windy North German course. Perfect for age-groupers chasing qualifiers without climbing suffering. Cobbles and false flats prevent pure TT boredom.",
      "strengths": [],
      "weaknesses": [],
      "bottom_line": ""
    },
    "final_verdict": {
      "score": "64/100",
      "one_liner": "T2 GFNY franchise event: Fast Euro qualifier with wind character",
      "should_you_race": "",
      "alternatives": ""
    },
    "citations": [],
    "youtube_data": {
      "researched_at": "2026-03-05",
      "search_query": "GFNY Bremen gran fondo cycling Bremen",
      "videos": [
        {
          "video_id": "R4Dym4GWFT8",
          "title": "GFNY Bremen 2025 | Incredible First Edition",
          "channel": "GFNY World",
          "view_count": 169,
          "upload_date": "20251220",
          "duration_string": "50",
          "description": "more info: bremen.gfny.com\n\n#gfny #cycling #granfondo",
          "tags": [],
          "url": "https://www.youtube.com/watch?v=R4Dym4GWFT8",
          "transcript": "Heat. Heat.",
          "curated": false
        },
        {
          "video_id": "q5co8x9Jw8A",
          "title": "Wie schnell sind Jedermannrennen wirklich? | GFNY Bremen",
          "channel": "GCN auf Deutsch",
          "view_count": 118575,
          "upload_date": "20250920",
          "duration_string": "15:53",
          "description": "Wie schnell sind Jedermannrennen wirklich und kann da jeder mithalten? Wir haben uns dieser Frage gestellt und sind beim GFNY Gran Fondo in Bremen an den Start gegangen. Begleitet uns auf 112 Kilometern voller Rennaction, taktischer Manöver auf der Windkante und einem packenden Finale. Dieses Video zeigt die volle Erfahrung: von der Vorbereitung über die nervöse Startphase bis hin zu einem dramatischen Zielsprint, der erst durch ein Foto-Finish entschieden wurde. Ein authentischer Einblick in die Welt der Gran Fondos, der zeigt, wie hart, aber auch wie unglaublich faszinierend diese Rennen sind.\n\nIn bezahlter Werbepartnerschaft mit GFNY & @insta360 \nhttps://gfny.com/\nhttps://store.insta360.com/product/x5?c=INRZZLD\n\nWerde Mitglied des Kanals und sichere dir viele Vorteile und Bonus-Content:\nhttps://gcn.eu/JoinGCNaufDeutsch\n\nDu hast eine Frage? \n\nDu hast eine Frage zum Video, oder dir brennt schon länger eine allgemeine Frage zum Thema Radsport auf der Seele? Dann kommentiere einfach unter dem Video mit dem #fraggcn . Wir werden uns dann in unserer monatlichen Serie \"Frag GCN\", hier auf YouTube, so vielen Fragen wie möglich widmen. \n\nTimestamps \n00:00 - Intro: Können wir ein Jedermannrennen gewinnen?\n00:27 - Die Vorbereitung: Startnummern & Taktik\n02:02 - Unser Kamera-Setup\n02:46 - Der Start\n03:25 - Die erste Rennhälfte: Attacken & hohes Tempo\n04:36 - Rennanalyse & Streckeninformationen\n05:07 - Die zweite Runde: Taktik auf der Windkante\n06:19 - Kurze Verschnaufpause und Gespräche im Feld\n07:38 - Anschluss zur Führungsgruppe\n09:30 - Was ist GFNY?\n10:20 - Das Finale\n12:58 - Die Siegerehrung und Ausklang\n13:48 - Was sagt der GFNY-Gründer?\n15:00 - Fazit\n\nInteressante Links\n\nWerde Teil des offiziellen GCNxStrava-Clubs \n🔗 https://gcn.eu/stravaclub .\n \n Lust auf mehr Videos? \n\n▶️ Memberships 👉 https://gcn.eu/JYTM\n📹 Eines unserer Lieblingsvideos 👉 https://gcn.eu/Lieblingsvideos\n📹 Eines unserer Highlights vom Außendreh 👉 https://gcn.eu/Highlights\n📹 Unsere wöchentliche Show 👉 https://gcn.eu/GCNaufDeutschShow\n \nMusik \n🎵Lizenziert bei Epidemic Sound 🎵\n\n\n#gcn #gcnaufdeutsch #rennrad #fahrrad\n \n© Velo Collection (TDW) / Getty Images \n© Sirotti / https://www.sirotti.it/\n \nWer wir sind  \nWillkommen bei GCN auf Deutsch - von den Köpfen hinter Global Cycling Network (GCN). Wir bringen jede Woche neue Radsportvideos auf Deutsch. Wir machen euch schneller und besser auf dem Rad! - egal ob Rennrad, Cross-Rad oder Gravel-bike. Unser Presenter Team aus Ex-Radprofis hilft gerne weiter! Jeden Dienstag bringen wir in der GCN auf Deutsch Show aktuelle News aus dem Radsport. Seid ein Teil von YouTubes größter und bester Radsport-Channel Gruppe, jetzt auch auf Deutsch!\n\nGCN auf Deutsch ist ein Kanal von Play Sports Network Limited, einem Unternehmen, das im Handelsregister von England und Wales eingetragen ist.\n \nFolgt uns!\n📱 Facebook: https://gcn.eu/gcnaufdeutsch-facebook\n📱 Instagram: https://gcn.eu/Instagram-GCNDeu\n📱 Twitter: https://gcn.eu/gcnaufdeutsch-twitter\n📱 TikTok: https://gcn.eu/gcnaufdeutsch-tiktok\n \nMehr von GCN \nGMBN: https://gmbn.eu/YouTube\nGMBN Tech: https://gmbn.tech/YouTube\nEMBN: https://embn.me/YouTube\nGCN: https://gcn.eu/YouTube\nGCN Tech: https://gcntech.co/YouTube\nGTN: https://gtn.io/YouTube\nGCN en Español: https://gcn.eu/EspanolYouTube\nGCN Italia: https://gcn.eu/ItaliaYouTube\nGCN en Francais: https://gcn.eu/FrancaisYouTube\nGCN Training: https://gcn.eu/TrainingYouTube\nGCN Racing: https://gcn.eu/RacingYouTube\n\nDanke an unsere Sponsoren:\nCanyon: https://gcn.eu/canyon-de\nCamelBak: https://gcn.eu/CamelbakDe\nClose The Gap: https://gcn.eu/CloseTheGap\nContinental: https://gcn.eu/continental\nHunt Wheels: https://gcn.eu/hunt\nMyVelo: https://gcn.eu/myvelo\nPark Tool: https://gcn.eu/ParktoolDE\nSelle Italia: https://gcn.eu/SelleItaliaDE\nSidi: https://gcn.eu/SidiShoes\nSilca: https://gcn.eu/SilcaEUGCN\nVan Rysel: https://gcn.eu/VanRyselDE\nWahoo: https://gcn.eu/wahoo-de\nZwift: https://gcn.eu/Zwift-de",
          "tags": [
            "Jedermannrennen",
            "Gran Fondo",
            "GFNY Bremen",
            "Radrennen",
            "Zielsprint",
            "Foto-Finish",
            "Renntaktik",
            "Windkante",
            "Radsport",
            "Rennrad",
            "Insta360",
            "POV Radrennen",
            "Onboard Kamera",
            "Bremen",
            "GCN Deutsch",
            "Radmarathon",
            "Hobbyrennen",
            "Radsport für alle",
            "Bremer Roland",
            "Global Cycling Network",
            "Fahrrad",
            "Cycling",
            "GCN",
            "radfahren",
            "GCN auf Deutsch",
            "Rad",
            "bicycle",
            "Radfahrer",
            "velo",
            "fahrrad fahren",
            "rennrad fahren",
            "deutsch",
            "rennrad training",
            "rennrad tipps",
            "Laurin Winter",
            "Patrick Haller",
            "ቋ",
            "ማ",
            "㈐",
            "㈴",
            "㉑",
            "꛶",
            "ꗶ",
            "Ղ",
            "g3",
            "ፕ15",
            "𑣬‎",
            "ꤚ",
            "𑫷‎",
            "ㅩ",
            "𐒎",
            "㈥",
            "ዩ",
            "ꚢ",
            "ጻ",
            "፻",
            "ኜ",
            "Ձ",
            "5920"
          ],
          "url": "https://www.youtube.com/watch?v=q5co8x9Jw8A",
          "curated": true,
          "curation_reason": "High-quality GCN production with race analysis covering tactics, wind conditions, and photo finish drama over 112km course.",
          "display_order": 1,
          "thumbnail_url": "https://i.ytimg.com/vi/q5co8x9Jw8A/maxresdefault.jpg",
          "thumbnail_score": 84.0
        },
        {
          "video_id": "fqc-nr8pX6I",
          "title": "GFNY BREMEN. The course",
          "channel": "GFNY World",
          "view_count": 667,
          "upload_date": "20250714",
          "duration_string": "51",
          "description": "more info:  https://bremen.gfny.com/strecke/",
          "tags": [],
          "url": "https://www.youtube.com/watch?v=fqc-nr8pX6I",
          "transcript": "[Music]\nHeat up here.\nHeat. Heat.",
          "curated": false
        },
        {
          "video_id": "CmGVBM_d-W8",
          "title": "GFNY is coming to Germany: GFNY Bremen 2025!",
          "channel": "GFNY World",
          "view_count": 1171,
          "upload_date": "20240919",
          "duration_string": "33",
          "description": "more info: https://bremen.gfny.com/",
          "tags": [],
          "url": "https://www.youtube.com/watch?v=CmGVBM_d-W8",
          "transcript": "[Music]\ngo\n[Applause]",
          "curated": false
        },
        {
          "video_id": "9pUQWkVo_q0",
          "title": "GFNY Bremen 2025  -  my full race video  ( frontcamera )",
          "channel": "Marc Gielen",
          "view_count": 222,
          "upload_date": "20250913",
          "duration_string": "3:18:03",
          "description": "",
          "tags": [
            "GFNY",
            "GFNY Bremen",
            "Bremen",
            "Germany",
            "Deutchland",
            "gran fondo",
            "cycling",
            "race"
          ],
          "url": "https://www.youtube.com/watch?v=9pUQWkVo_q0",
          "curated": true,
          "curation_reason": "Complete first-person race experience with front camera footage showing the full course and race conditions.",
          "display_order": 2,
          "thumbnail_url": "https://i.ytimg.com/vi/9pUQWkVo_q0/maxresdefault.jpg",
          "thumbnail_score": 88.07
        }
      ],
      "quotes": []
    }
  }
}
